<?xml-stylesheet type='text/xsl' href='./ShapeChangeDefinitionsType.xsl'?><TypeDefinition xmlns="http://www.interactive-instruments.de/ShapeChange/Definitions/0.5" xmlns:def="http://www.interactive-instruments.de/ShapeChange/Definitions/0.5" xmlns:gml="http://www.opengis.net/gml/3.2" xmlns:xlink="http://www.w3.org/1999/xlink" xmlns:xsi="http://www.w3.org/2001/XMLSchema-instance" gml:id="S.164.1805.46.340" xsi:schemaLocation="http://www.interactive-instruments.de/ShapeChange/Definitions/0.5 ShapeChangeDefinitions.xsd">
  <description xmlns="http://www.opengis.net/gml/3.2">[K] 'Ast' ist ein Teil des Straßennetzes, der zur Verknüpfung der Abschnitte untereinander dient und deshalb Teil des Netzknotens ist. Er wird durch die im Netzknoten festgelegten Nullpunkte begrenzt.                                        

</description>
  <identifier xmlns="http://www.opengis.net/gml/3.2" codeSpace="http://www.interactive-instruments.de/ShapeChange/Definitions/0.5">urn:x-shapechange:def:featureType:GeoInfoDok::adv:6.0.1:AX_Ast</identifier>
  <name xmlns="http://www.opengis.net/gml/3.2" codeSpace="http://www.interactive-instruments.de/ShapeChange/Definitions/0.5/name">AX_Ast</name>
  <dictionaryEntry xmlns="http://www.opengis.net/gml/3.2">
    <PropertyDefinition xmlns="http://www.interactive-instruments.de/ShapeChange/Definitions/0.5" gml:id="S.164.1805.46.342">
      <description xmlns="http://www.opengis.net/gml/3.2">Angaben zur Herkunft der Informationen (Erhebungsstelle, Art der Datenerhebung).</description>
      <identifier xmlns="http://www.opengis.net/gml/3.2" codeSpace="http://www.interactive-instruments.de/ShapeChange/Definitions/0.5">urn:x-shapechange:def:propertyType:GeoInfoDok::adv:6.0.1:AX_Ast:qualitaetsangaben</identifier>
      <name xmlns="http://www.opengis.net/gml/3.2" codeSpace="http://www.interactive-instruments.de/ShapeChange/Definitions/0.5/name">qualitaetsangaben</name>
      <cardinality>0..1</cardinality>
      <valueTypeRef xlink:href="urn:x-shapechange:def:dataType:GeoInfoDok::adv:6.0.1:AX_DQMitDatenerhebung"/>
      <type>attribute</type>
    </PropertyDefinition>
  </dictionaryEntry>
  <dictionaryEntry xmlns="http://www.opengis.net/gml/3.2">
    <PropertyDefinition xmlns="http://www.interactive-instruments.de/ShapeChange/Definitions/0.5" gml:id="S.164.1805.46.341">
      <description xmlns="http://www.opengis.net/gml/3.2">'Bezeichnung' ist die von einer Fachstelle vergebene Kennziffer von 'Ast'.</description>
      <identifier xmlns="http://www.opengis.net/gml/3.2" codeSpace="http://www.interactive-instruments.de/ShapeChange/Definitions/0.5">urn:x-shapechange:def:propertyType:GeoInfoDok::adv:6.0.1:AX_Ast:bezeichnung</identifier>
      <name xmlns="http://www.opengis.net/gml/3.2" codeSpace="http://www.interactive-instruments.de/ShapeChange/Definitions/0.5/name">bezeichnung</name>
      <cardinality>1</cardinality>
      <valueTypeName>CharacterString</valueTypeName>
      <type>attribute</type>
    </PropertyDefinition>
  </dictionaryEntry>
  <dictionaryEntry xmlns="http://www.opengis.net/gml/3.2">
    <PropertyDefinition xmlns="http://www.interactive-instruments.de/ShapeChange/Definitions/0.5" gml:id="G.227">
      <description xmlns="http://www.opengis.net/gml/3.2">
      </description>
      <identifier xmlns="http://www.opengis.net/gml/3.2" codeSpace="http://www.interactive-instruments.de/ShapeChange/Definitions/0.5">urn:x-shapechange:def:propertyType:GeoInfoDok::adv:6.0.1:AX_Ast:inversZu_gehoertZuBauwerk</identifier>
      <name xmlns="http://www.opengis.net/gml/3.2" codeSpace="http://www.interactive-instruments.de/ShapeChange/Definitions/0.5/name">inversZu_gehoertZuBauwerk</name>
      <cardinality>0..*</cardinality>
      <valueTypeRef xlink:href="urn:x-shapechange:def:featureType:GeoInfoDok::adv:6.0.1:AX_SonstigesBauwerkOderSonstigeEinrichtung"/>
      <type>associationRole</type>
    </PropertyDefinition>
  </dictionaryEntry>
  <classification>featureType</classification>
  <supertypeRef xlink:href="urn:x-shapechange:def:featureType:GeoInfoDok::adv:6.0.1:AU_KontinuierlichesLinienobjekt"/>
</TypeDefinition>
